shapfs/__init__.py
shapfs/feature_selection.py
shapfs_0.0.1-0.0.1.dist-info/LICENSE
shapfs_0.0.1-0.0.1.dist-info/METADATA
shapfs_0.0.1-0.0.1.dist-info/WHEEL
shapfs_0.0.1-0.0.1.dist-info/top_level.txt
shapfs_0.0.1-0.0.1.dist-info/RECORD
